cocalc_api/__init__.py
cocalc_api/api_types.py
cocalc_api/hub.py
cocalc_api/org.py
cocalc_api/project.py
cocalc_api/py.typed
cocalc_api/util.py
cocalc_api/mcp/__init__.py
cocalc_api/mcp/__main__.py
cocalc_api/mcp/mcp_debug.py
cocalc_api/mcp/mcp_server.py
cocalc_api/mcp/server.py
cocalc_api/mcp/resources/__init__.py
cocalc_api/mcp/resources/account_profile.py
cocalc_api/mcp/resources/file_listing.py
cocalc_api/mcp/tools/__init__.py
cocalc_api/mcp/tools/exec.py
cocalc_api/mcp/tools/jupyter.py
cocalc_api/mcp/tools/project_state.py
cocalc_api/mcp/tools/project_status.py
cocalc_api/mcp/tools/projects_search.py
cocalc_api-0.5.0.dist-info/METADATA
cocalc_api-0.5.0.dist-info/WHEEL
cocalc_api-0.5.0.dist-info/entry_points.txt
cocalc_api-0.5.0.dist-info/top_level.txt
cocalc_api-0.5.0.dist-info/RECORD
