Metadata-Version: 2.4
Name: cocalc-api
Version: 0.5.0
Summary: Python client for the CoCalc API
Author-email: William Stein <wstein@sagemath.com>, Harald Schilly <hsy@sagemath.com>
License-Expression: MIT
Project-URL: Homepage, https://github.com/sagemathinc/cocalc/src/python/cocalc-api
Project-URL: Repository, https://github.com/sagemathinc/cocalc
Project-URL: Documentation, https://cocalc.com/api/python
Project-URL: Source, https://github.com/sagemathinc/cocalc/src/python/cocalc-api
Project-URL: Issues, https://github.com/sagemathinc/cocalc/issues
Requires-Python: >=3.10
Requires-Dist: httpx
Requires-Dist: mcp>=0.1.0
